statebase/__init__.py
statebase/async_client.py
statebase/client.py
statebase/models.py
statebase-0.2.0.dist-info/METADATA
statebase-0.2.0.dist-info/WHEEL
statebase-0.2.0.dist-info/top_level.txt
statebase-0.2.0.dist-info/RECORD
