Metadata-Version: 2.4
Name: statebase
Version: 0.2.0
Summary: The Reliability Layer for Production AI Agents
Home-page: https://github.com/StateBase/statebase-python
Author: StateBase Team
Author-email: hello@statebase.org
Project-URL: Bug Reports, https://github.com/StateBase/statebase-python/issues
Project-URL: Source, https://github.com/StateBase/statebase-python
Keywords: ai,agents,memory,state,llm
Classifier: Development Status :: 3 - Alpha
Classifier: Intended Audience :: Developers
Classifier: Topic :: Software Development :: Libraries :: Python Modules
Classifier: License :: OSI Approved :: MIT License
Classifier: Programming Language :: Python :: 3
Classifier: Programming Language :: Python :: 3.9
Classifier: Programming Language :: Python :: 3.10
Classifier: Programming Language :: Python :: 3.11
Requires-Python: >=3.9
Requires-Dist: httpx>=0.24.0
Requires-Dist: pydantic>=2.0.0
Requires-Dist: typing-extensions>=4.0.0
Dynamic: author
Dynamic: author-email
Dynamic: classifier
Dynamic: description
Dynamic: description-content-type
Dynamic: home-page
Dynamic: keywords
Dynamic: project-url
Dynamic: requires-dist
Dynamic: requires-python
Dynamic: summary
